{
  "description": "Import mapping for LUKHAS module reorganization",
  "mappings": {
    "consciousness.core": "consciousness.core_consciousness",
    "consciousness.stream": "consciousness.stream_consciousness",
    "memory.unified_memory_system": "memory.core",
    "memory.systems.memory_fold_system": "memory.systems.memory_fold",
    "orchestration.agi_brain_orchestrator": "orchestration.brain.agi_brain_orchestrator",
    "orchestration.orchestrator": "orchestration.core_orchestrator",
    "bio.symbolic": "symbolic.bio",
    "bio.systems": "bio.systems.orchestration",
    "features.memory": "memory.features",
    "features.integration": "integration.features"
  },
  "import_completions": {
    "dataclasses": [
      "dataclass",
      "field",
      "asdict",
      "astuple"
    ],
    "typing": [
      "Dict",
      "List",
      "Any",
      "Optional",
      "Union",
      "Tuple",
      "Set"
    ],
    "pathlib": [
      "Path",
      "PurePath"
    ],
    "datetime": [
      "datetime",
      "timedelta",
      "timezone"
    ],
    "collections": [
      "defaultdict",
      "Counter",
      "deque",
      "OrderedDict"
    ]
  }
}